Workbook

Sheet 说明
A1: 软件项目供应商评审评分表（最终版）
A3: 项目 | B3: 内容
A4: 编制原则 | B4: 以资质评分、定制开发评分、驻场运维评分、统一报价四张评分页分别独立评分、汇总页统一加权为原则编制。
A5: 资质评分规则 | B5: 第一页为100分制资质评分，作为综合评分组成部分。项目如有刚性资格门槛，应在采购文件中另行明确，不在本页以通过/不通过方式体现。
A6: 权重规则 | B6: 同一项目必须对全部供应商采用统一权重，不得因供应商不同而分别设置权重。
A7: 价格规则 | B7: 默认采用常见的最低有效报价比例法：最低有效报价/本供应商有效报价×价格分值。
A8: 使用建议 | B8: 资质评分、定制开发评分、驻场运维评分、统一报价评分四页各自满分100分；在“汇总排名”页设置四项权重后自动汇总为综合评审得分。
A9: 使用步骤
A10: 1. 在“资质评分”页录入各供应商原始分；第一页细项分值合计为100分。
A11: 2. 在“定制开发评分”和“驻场运维评分”页分别录入原始分；每页细项分值合计均为100分。
A12: 3. 在“统一报价评分”页录入各供应商针对本项目整包的有效报价；本页满分100分。
A13: 4. 在“汇总排名”页统一设置资质评分、定制开发、驻场运维、统一报价四项权重，四项权重合计应为100%。
A14: 5. 如采购文件另有专门价格评审办法、专门资格条件或评分细则，应在发文前按项目文件统一调整，不得在评审中临时改动。
A15: 推荐权重示例 | B15: 资质评分权重 | C15: 定制开发权重 | D15: 驻场运维权重 | E15: 统一报价权重 | F15: 权重合计 | G15: 适用说明
A16: 纯定制开发项目 | B16: 20 | C16: 50 | D16: 0 | E16: 30 | F16: 100 | G16: 适用于以需求调研、设计开发、测试上线为主的项目。
A17: 纯驻场运维项目 | B17: 20 | C17: 0 | D17: 50 | E17: 30 | F17: 100 | G17: 适用于以驻场支持、故障处理、持续服务为主的项目。
A18: 综合服务项目 | B18: 20 | C18: 30 | D18: 20 | E18: 30 | F18: 100 | G18: 适用于开发建设、驻场保障及整包报价同时纳入综合评审的项目。
A20: 建议取证材料
A21: - 营业执照、税务开票能力证明、信用承诺或信用查询结果。
A22: - 同类项目合同关键页、验收单、发票或回款证明等业绩支撑材料。
A23: - 项目经理及核心成员简历、社保或劳动关系证明、岗位分工表。
A24: - 总体技术方案、实施计划、WBS/里程碑、风险控制方案、服务承诺书。
A25: - 体系认证、软件著作权、行业资质、保密/安全承诺等证明材料。

Sheet 资质评分
A1: 资质评分
A2: 适用于对供应商企业基础能力、财务实力、同类项目业绩、企业信誉及基础资质等内容进行综合评分。本页作为综合评审组成部分，页内满分100分。
A3: 填写规则：仅录入蓝色单元格；专家原始分不得超过C列分值；本页统计供应商基础资质与综合能力得分，不再设置通过/不通过结论。
A4: 评审大项 | B4: 评审子项 | C4: 分值 | D4: 评分标准 | E4: 评分依据/证明材料 | F4: 诚迈科技原始分 | G4: 晶石科技原始分 | H4: 南京亿顺弘原始分 | I4: 备注
A5: 企业规模与综合实力 | B5: 企业规模与综合实力 | C5: 20 | D5: 根据近三年平均人均资产额、人均利润水平、纳税规模及企业整体实力综合评定。指标表现优秀、企业规模及综合实力较强，得20分；表现较好，得15-19分；表现一般，得8-14分；较弱或未提供有效证明材料，得0-7分。 | E5: 近三年审计报告、纳税证明、企业基本情况说明等。
A6: 财务状况 | B6: 财务状况 | C6: 20 | D6: 根据近三年平均净利率、主营业务收入、盈利稳定性和财务健康程度综合评定。财务状况良好、持续盈利能力强、资金实力稳定，得20分；财务状况较好，得15-19分；财务状况一般，得8-14分；较弱、出现连续亏损或未提供有效证明材料，得0-7分。 | E6: 近三年审计报告、财务报表及相关财务情况说明等。
A7: 同类项目业绩 | B7: 同类项目业绩 | C7: 20 | D7: 以投标截止时间前三年内的同类项目合同为准，结合合同数量、合同金额、项目类型匹配度及验收情况综合评定。业绩数量充足、至少提供1份30万元及以上同类项目合同，且验收证明完整、相关性高，得20分；业绩较好，得15-19分；业绩一般，得8-14分；业绩较少、相关性较弱、金额不足或证明材料不完整，得0-7分。 | E7: 同类项目合同关键页、验收证明、用户评价材料、项目成果说明、发票或回款证明等。
A8: 企业信誉与合规情况 | B8: 企业信誉与合规情况 | C8: 20 | D8: 近三年无重大违法失信、无重大质量安全事故、无严重违约情形，信用记录良好，响应材料真实、完整、可核验，得20分；存在轻微瑕疵但不影响实质履约能力，得15-19分；信用或合规支撑一般，得8-14分；存在严重失信、重大违法违规、严重违约或材料失实情形，得0-7分。 | E8: 信用承诺函、信用查询结果、无重大违法记录声明、无重大质量安全事故声明、材料真实性承诺等。
A9: 基础资质、安全保密与专门条件响应 | B9: 基础资质、安全保密与专门条件响应 | C9: 20 | D9: 具备有效主体资格，能够开具合法合规发票，满足项目要求的安全、保密及现场管理要求，并对采购文件规定的专门资质、授权及商务条款作出完整响应，得20分；响应较完整，得15-19分；响应一般或部分材料欠缺，得8-14分；缺少关键资质、授权、安全保密承诺或专门条件响应明显不足，得0-7分。 | E9: 营业执照、开票能力证明、保密承诺、安全管理制度、专项资质、授权文件、商务响应文件等。
A10: 资质评分小计 | C10: 100 | D10: 本行自动汇总本页技术商务得分，不含统一报价得分。 | F10: =ROUND(SUM(F5:F9),2) -> 0 | G10: =ROUND(SUM(G5:G9),2) -> 0 | H10: =ROUND(SUM(H5:H9),2) -> 0

Sheet 定制开发评分
A1: 定制开发评分
A2: 适用于以需求调研、系统设计、开发测试、上线交付为主的软件项目。本页按“开发特有能力”为主设置评分项，已对与驻场运维页重复的通用项做去重处理，页内满分 100 分。
A3: 填写规则：仅录入蓝色单元格；专家原始分不得超过 C 列分值；本页仅统计技术商务分，不含统一报价得分。
A4: 评审大项 | B4: 评审子项 | C4: 分值 | D4: 评分标准 | E4: 评分依据/证明材料 | F4: 诚迈科技原始分 | G4: 晶石科技原始分 | H4: 南京亿顺弘原始分 | I4: 备注
A5: 项目理解与需求分析 | B5: 需求理解与场景匹配度 | C5: 15 | D5: 对项目背景、建设目标、核心需求、业务场景和目标拆解理解准确，问题识别到位且针对性强，得 15 分；理解较准确、场景匹配较好但分析深度一般，得 8-14 分；理解偏差明显、针对性不足或内容空泛，得 0-7 分。 | E5: 需求响应、现状分析、问题清单、项目目标说明、业务场景分析、用户画像、流程梳理成果。
B6: 范围边界与关键难点识别 | C6: 6 | D6: 对项目边界、接口边界和关键难点识别完整，得 6 分；识别基本到位，得 3-5 分；识别不足，得 0-2 分。 | E6: 边界清单、关键风险点、约束条件说明。
A7: 技术方案与架构设计 | B7: 总体架构与功能方案合理性 | C7: 19 | D7: 总体架构完整、技术路线成熟可行，功能设计覆盖主要需求并体现关键场景，与项目目标高度匹配，得 19 分；方案较完整、合理性较好，得 10-18 分；架构或功能方案缺项明显、合理性较弱，得 0-9 分。 | E7: 总体架构图、技术选型说明、部署方案、功能清单、原型图、模块设计说明。
B8: 接口、数据与安全设计 | C8: 8 | D8: 接口衔接、数据流向、安全控制设计清楚，得 8 分；基本具备，得 4-7 分；说明不足，得 0-3 分。 | E8: 接口清单、数据模型、安全方案。
B9: 可扩展性与可实施性 | C9: 7 | D9: 方案具备扩展性、兼容性和可实施路径，得 7 分；一般，得 4-6 分；可实施性弱，得 0-3 分。 | E9: 实施路径、环境适配说明、扩展设计。
A10: 实施计划与项目管理 | B10: 实施计划、风险与质量控制 | C10: 15 | D10: 阶段划分、里程碑、关键交付节点清晰可执行，且具备完整的风险识别、预警、应对和质量控制机制，得 15 分；计划较清晰、风险和质量控制机制基本可行，得 8-14 分；安排粗略或控制机制缺失，得 0-7 分。 | E10: WBS、里程碑计划、甘特图、风险台账、测试策略、质量控制流程。
B11: 交付物定义与验收安排 | C11: 6 | D11: 交付物清单、输出形式、验收方式明确，得 6 分；基本明确，得 3-5 分；不明确，得 0-2 分。 | E11: 交付物清单、验收计划、文档目录。
A12: 团队配置与履约能力 | B12: 项目团队配置与履约能力 | C12: 14 | D12: 项目经理及核心成员经验丰富、履历与项目高度匹配，产品、设计、开发、测试、实施等关键岗位配置齐全且职责清晰，得 14 分；基本匹配且岗位较齐备，得 8-13 分；匹配度较低或岗位明显缺失，得 0-7 分。 | E12: 人员简历、项目经历、证书、社保证明、组织架构图、岗位分工、人员清单。
A13: 软件交付经验与技术能力 | B13: 同类软件交付经验与技术能力 | C13: 10 | D13: 同类案例数量充足、与本项目行业和复杂度高度相关，且具备与项目匹配的体系认证或专业资质、研发能力证明，得 10 分；案例或资质匹配度一般，得 5-9 分；案例较弱或无有效资质，得 0-4 分。 | E13: 软件开发或系统建设项目合同关键页、验收证明、成果材料、研发类资质、软著、专利、技术能力证明。
A14: 技术商务小计 | C14: 100 | D14: 本行自动汇总本页技术商务得分，不含统一报价得分。 | F14: =ROUND(SUM(F5:F13),2) -> 0 | G14: =ROUND(SUM(G5:G13),2) -> 0 | H14: =ROUND(SUM(H5:H13),2) -> 0

Sheet 驻场运维评分
A1: 驻场运维评分
A2: 适用于以驻场研发、运维支持、持续服务和响应保障为主的项目。本页按“驻场运维特有能力”为主设置评分项，已对与定制开发页重复的通用项做去重处理，页内满分 100 分。
A3: 填写规则：仅录入蓝色单元格；专家原始分不得超过 C 列分值；本页仅统计技术商务分，不含统一报价得分。
A4: 评审大项 | B4: 评审子项 | C4: 分值 | D4: 评分标准 | E4: 评分依据/证明材料 | F4: 诚迈科技原始分 | G4: 晶石科技原始分 | H4: 南京亿顺弘原始分 | I4: 备注
A5: 服务理解与方案设计 | B5: 服务范围与流程理解 | C5: 13 | D5: 对服务范围、职责边界、支持边界理解准确，服务流程、工单流转、例会与报告机制完整，得 13 分；基本准确且机制较完整，得 7-12 分；理解偏差明显或机制不足，得 0-6 分。 | E5: 服务方案、范围说明、职责分工、服务流程图、报告模板、例会机制。
B6: 服务方案可执行性 | C6: 6 | D6: 方案执行路径清晰、适配采购场景，得 6 分；一般，得 3-5 分；可执行性弱，得 0-2 分。 | E6: 实施路径、现场协同方案。
A7: 驻场与响应保障 | B7: 驻场人员配置与稳定性保障 | C7: 20 | D7: 驻场人员数量充分、岗位结构合理、关键岗位齐备，且稳定性保障和替补机制明确，得 20 分；基本满足且稳定性安排较清晰，得 11-19 分；人员投入明显不足或替补机制较弱，得 0-10 分。 | E7: 驻场清单、岗位说明、资源投入计划、替补名单、稳定性承诺、人员管理机制。
B8: 响应时效与应急处置能力 | C8: 20 | D8: 响应时效、升级路径、闭环机制明确且优于基本要求，应急预案、重大故障处置和专项支撑能力强，得 20 分；基本满足要求，得 11-19 分；响应或应急处置能力较弱，得 0-10 分。 | E8: SLA、升级流程、值守安排、应急预案、值班机制、历史案例说明。
A9: 持续服务与知识交接 | B9: 知识交接与持续优化机制 | C9: 14 | D9: 知识沉淀、文档维护、培训交接安排完整，具备持续优化、例会复盘、改进闭环机制，得 14 分；较完整，得 8-13 分；安排或机制不足，得 0-7 分。 | E9: 知识库目录、交接计划、培训方案、复盘模板、改进机制、周报或月报样例。
A10: 同类项目经验与服务治理能力 | B10: 同类项目案例、资质与服务治理能力 | C10: 15 | D10: 具备较丰富的同类项目实施经验，案例与本项目业务场景、服务方式和复杂程度匹配度高，同时具备与项目实施、驻场服务相关的资质认证、服务管理制度和SLA治理机制，得15分；项目经验或服务治理能力较好，得8-14分；同类项目经验较少、匹配度一般，或资质及治理机制支撑较弱，得0-7分。 | E10: 同类项目合同关键页、验收证明、用户评价材料、项目成果说明、相关资质证书、服务管理制度文件、SLA治理机制说明等。
A11: 商务响应与文件质量 | B11: 商务响应与文件完整性 | C11: 12 | D11: 商务承诺明确、违约处理和资源补偿机制清晰，响应文件完整、结构清晰、排版规范、检索方便，得 12 分；整体较好，得 7-11 分；较弱，得 0-6 分。 | E11: 商务承诺函、违约处理条款响应、响应文件目录、盖章签字、版本控制。
A12: 技术商务小计 | C12: 100 | D12: 本行自动汇总本页技术商务得分，不含统一报价得分。 | F12: =ROUND(SUM(F5:F11),2) -> 0 | G12: =ROUND(SUM(G5:G11),2) -> 0 | H12: =ROUND(SUM(H5:H11),2) -> 0

Sheet 统一报价评分
A1: 统一报价评分
A2: 适用于本项目整包统一报价评分。供应商仅填写一份针对本次项目完整范围的有效报价；本页默认满分 100 分。 | J2: 诚迈科技有效报价 | K2: 晶石科技有效报价 | L2: 南京亿顺弘有效报价
A3: 填写规则：仅录入蓝色单元格；报价应为本项目整包统一有效报价，不再区分定制开发和驻场运维分别报价。
A4: 评审大项 | B4: 评审子项 | C4: 分值 | D4: 评分标准 | E4: 评分依据/证明材料 | F4: 诚迈科技得分 | G4: 晶石科技得分 | H4: 南京亿顺弘得分 | I4: 备注
A5: 价格评分 | B5: 统一报价得分 | C5: 100 | D5: 价格部分采用最低有效报价比例法，最低有效报价得满分 100 分，其他供应商按“最低有效报价/本供应商有效报价×100”折算。 | E5: 有效报价表、澄清函、报价一览表等。 | F5: =IF(OR($J$3="",COUNT($J$3:$L$3)=0),0,ROUND(MIN($J$3:$L$3)/$J$3*100,2)) -> 0 | G5: =IF(OR($K$3="",COUNT($J$3:$L$3)=0),0,ROUND(MIN($J$3:$L$3)/$K$3*100,2)) -> 0 | H5: =IF(OR($L$3="",COUNT($J$3:$L$3)=0),0,ROUND(MIN($J$3:$L$3)/$L$3*100,2)) -> 0
A6: 合计 | C6: 100 | D6: 本页满分 100 分。 | F6: =ROUND(F5,2) -> 0 | G6: =ROUND(G5,2) -> 0 | H6: =ROUND(H5,2) -> 0

Sheet 汇总排名
A1: 综合评审汇总及排名
A3: 项目统一权重设置 | B3: 数值 | C3: 说明
A4: 资质评分权重（%） | B4: 10
A5: 定制开发权重（%） | B5: 40
A6: 驻场运维权重（%） | B6: 20
A7: 统一报价权重（%） | B7: 30
A8: 权重合计（%） | B8: =SUM(B4:B7) -> 100
A10: 指标 | B10: 诚迈科技 | C10: 晶石科技 | D10: 南京亿顺弘 | E10: 说明
A11: 资质评分总分 | B11: =资质评分!F10 -> 0 | C11: =资质评分!G10 -> 0 | D11: =资质评分!H10 -> 0 | E11: 引用“资质评分”页评分小计，满分100分。
A12: 定制开发总分 | B12: =定制开发评分!F14 -> 0 | C12: =定制开发评分!G14 -> 0 | D12: =定制开发评分!H14 -> 0 | E12: 引用“定制开发评分”页技术商务小计，满分100分。
A13: 驻场运维总分 | B13: =驻场运维评分!F12 -> 0 | C13: =驻场运维评分!G12 -> 0 | D13: =驻场运维评分!H12 -> 0 | E13: 引用“驻场运维评分”页技术商务小计，满分100分。
A14: 统一报价总分 | B14: =统一报价评分!F6 -> 0 | C14: =统一报价评分!G6 -> 0 | D14: =统一报价评分!H6 -> 0 | E14: 引用“统一报价评分”页合计分，满分100分。
A15: 综合评审得分 | B15: =ROUND(B11*$B$4/100+B12*$B$5/100+B13*$B$6/100+B14*$B$7/100,2) -> 0 | C15: =ROUND(C11*$B$4/100+C12*$B$5/100+C13*$B$6/100+C14*$B$7/100,2) -> 0 | D15: =ROUND(D11*$B$4/100+D12*$B$5/100+D13*$B$6/100+D14*$B$7/100,2) -> 0 | E15: 综合得分=资质评分×资质评分权重+定制开发总分×定制开发权重+驻场运维总分×驻场运维权重+统一报价总分×统一报价权重。
A16: 综合排名 | B16: =RANK(B15,$B$15:$D$15,0) -> 1 | C16: =RANK(C15,$B$15:$D$15,0) -> 1 | D16: =RANK(D15,$B$15:$D$15,0) -> 1 | E16: 按综合得分由高到低排名，分值相同则并列。
A18: 补充说明
A19: 1. 如项目只适用部分评分页，可将不适用部分权重设置为 0。
A20: 2. 请确保 B4:B7 四项权重合计为 100；B8 为自动校验值。
A21: 3. 如采购文件采用基准价法或其他价格评审办法，应在“统一报价评分”页统一替换价格公式。
A22: 4. 本模板为通用正式版，项目特有的资质门槛、授权要求、涉密要求应根据采购文件另行补充。
