Workbook

Sheet 说明
A1: 软件项目供应商评审评分表（最终版）
A3: 项目 | B3: 内容
A4: 适用场景 | B4: 适用于软件定制开发、研发服务、驻场运维、系统集成配套开发等供应商比选或询比场景。
A5: 编制原则 | B5: 以资格性审查先行、定制开发/驻场运维/统一报价三张评分页分别独立评分、汇总页统一加权为原则编制。
A6: 资格规则 | B6: 资格审查任一强制性条款判定“不通过”，该供应商不进入详细评分和排名。
A7: 权重规则 | B7: 同一项目必须对全部供应商采用统一权重，不得因供应商不同而分别设置权重。
A8: 价格规则 | B8: 默认采用常见的最低有效报价比例法：最低有效报价/本供应商有效报价×价格分值。
A9: 使用建议 | B9: 定制开发评分、驻场运维评分、统一报价评分三页各自满分 100 分；在“汇总排名”页设置三项权重后自动汇总为综合评审得分。
A11: 使用步骤
A12: 1. 在“资格审查”页填报各供应商资格结论，蓝色单元格可编辑。
A13: 2. 在“定制开发评分”和“驻场运维评分”页分别录入原始分；每页细项分值合计均为 100 分。
A14: 3. 在“统一报价评分”页录入各供应商针对本项目整包的有效报价；本页满分 100 分。
A15: 4. 在“汇总排名”页统一设置定制开发、驻场运维、统一报价三项权重，三项权重合计应为 100%。
A16: 5. 如采购文件另有专门价格评审办法、专门资格条件或评分细则，应在发文前按项目文件统一调整，不得在评审中临时改动。
A19: 推荐权重示例 | B19: 定制开发权重 | C19: 驻场运维权重 | D19: 统一报价权重 | E19: 权重合计 | F19: 适用说明
A20: 纯定制开发项目 | B20: 60 | C20: 0 | D20: 40 | E20: 100 | F20: 适用于以需求调研、设计开发、测试上线为主的项目。
A21: 纯驻场运维项目 | B21: 0 | C21: 60 | D21: 40 | E21: 100 | F21: 适用于以驻场支持、故障处理、持续服务为主的项目。
A22: 综合服务项目 | B22: 40 | C22: 30 | D22: 30 | E22: 100 | F22: 适用于开发建设与驻场保障同时存在的项目。
A25: 建议取证材料
A26: - 营业执照、税务开票能力证明、信用承诺或信用查询结果。
A27: - 同类项目合同关键页、验收单、发票或回款证明等业绩支撑材料。
A28: - 项目经理及核心成员简历、社保或劳动关系证明、岗位分工表。
A29: - 总体技术方案、实施计划、WBS/里程碑、风险控制方案、服务承诺书。
A30: - 体系认证、软件著作权、行业资质、保密/安全承诺等证明材料。

Sheet 资格审查
A1: 资格性及符合性审查表
A2: 说明：任一强制性条款判定“不通过”，该供应商不得进入详细评分；“待确认”仅用于评审前补证核验，不得用于已终结评审。
A4: 序号 | B4: 资格审查项 | C4: 审查要求/判定标准 | D4: 供应商A | E4: 供应商B | F4: 供应商C
A5: 1 | B5: 主体资格 | C5: 依法设立并有效存续，提供营业执照或同等主体资格证明。 | D5: 通过 | E5: 通过 | F5: 通过
A6: 2 | B6: 开票能力 | C6: 能够开具合法合规发票，并满足采购文件约定的税务要求。
A7: 3 | B7: 信誉要求 | C7: 近三年无重大违法失信记录、无重大质量安全事故、无严重违约情形。
A8: 4 | B8: 技术与服务能力 | C8: 具备承担本项目所需的技术、工具、方法、管理和服务能力。
A9: 5 | B9: 最低团队要求 | C9: 满足采购文件规定的最低人员配置、驻场安排或响应时效要求。
A10: 6 | B10: 业绩及授权要求 | C10: 按采购文件要求提供同类业绩；如涉及代理、原厂授权或联合体要求，应提供有效授权/承诺。
A11: 7 | B11: 商务条款响应 | C11: 接受主要合同条款，包括交付、验收、付款、保密、知识产权、违约责任等。
A12: 8 | B12: 安全与保密 | C12: 满足网络安全、数据安全、保密及现场管理等强制性要求。
A13: 9 | B13: 材料真实性 | C13: 提交的资质、业绩、简历、承诺等材料真实、完整、可核验。
A14: 10 | B14: 其他专门条件 | C14: 满足采购文件另行约定的专门资格条件或实质性响应要求。
A15: 审查结论 | B15: 任一项不通过则结论为不通过；存在待确认或空白则结论为待确认；其余视为通过。 | D15: =IF(COUNTIF(D5:D14,"不通过")>0,"不通过",IF(COUNTIF(D5:D14,"待确认")+COUNTBLANK(D5:D14)>0,"待确认","通过")) -> 待确认 | E15: =IF(COUNTIF(E5:E14,"不通过")>0,"不通过",IF(COUNTIF(E5:E14,"待确认")+COUNTBLANK(E5:E14)>0,"待确认","通过")) -> 待确认 | F15: =IF(COUNTIF(F5:F14,"不通过")>0,"不通过",IF(COUNTIF(F5:F14,"待确认")+COUNTBLANK(F5:F14)>0,"待确认","通过")) -> 待确认

Sheet 定制开发评分
A1: 定制开发评分
A2: 适用于以需求调研、系统设计、开发测试、上线交付为主的软件项目。本页技术商务细项采用整数分值分配，页内满分 100 分。
A3: 填写规则：仅录入蓝色单元格；专家原始分不得超过 C 列分值；本页仅统计技术商务分，不含统一报价得分。
A4: 评审大项 | B4: 评审子项 | C4: 分值 | D4: 评分标准 | E4: 评分依据/证明材料 | F4: 诚迈科技原始分 | G4: 晶石科技原始分 | H4: 亿顺弘原始分 | I4: 备注
A5: 项目理解与需求分析 | B5: 需求理解准确性 | C5: 7 | D5: 对项目背景、建设目标、核心需求理解准确，问题识别到位，得 7 分；理解较为准确但分析深度一般，得 4-6 分；理解偏差明显或内容空泛，得 0-3 分。 | E5: 需求响应、现状分析、问题清单、项目目标说明。
B6: 业务场景与目标匹配度 | C6: 5 | D6: 能够结合采购场景提出针对性理解和目标拆解，得 5 分；匹配度一般，得 3-4 分；针对性不足，得 0-2 分。 | E6: 业务场景分析、用户画像、流程梳理成果。
B7: 范围边界与关键难点识别 | C7: 5 | D7: 对项目边界、接口边界和关键难点识别完整，得 5 分；识别基本到位，得 3-4 分；识别不足，得 0-2 分。 | E7: 边界清单、关键风险点、约束条件说明。
A8: 技术方案与架构设计 | B8: 总体架构与技术路线合理性 | C8: 8 | D8: 总体架构完整、技术路线成熟可行、与项目目标高度匹配，得 8 分；较为合理，得 4-7 分；合理性较弱，得 0-3 分。 | E8: 总体架构图、技术选型说明、部署方案。
B9: 功能方案完整性 | C9: 7 | D9: 功能设计覆盖主要需求并体现关键场景，得 7 分；覆盖较完整，得 4-6 分；缺项明显，得 0-3 分。 | E9: 功能清单、原型图、模块设计说明。
B10: 接口、数据与安全设计 | C10: 5 | D10: 接口衔接、数据流向、安全控制设计清楚，得 5 分；基本具备，得 3-4 分；说明不足，得 0-2 分。 | E10: 接口清单、数据模型、安全方案。
B11: 可扩展性与可实施性 | C11: 5 | D11: 方案具备扩展性、兼容性和可实施路径，得 5 分；一般，得 3-4 分；可实施性弱，得 0-2 分。 | E11: 实施路径、环境适配说明、扩展设计。
A12: 实施计划与项目管理 | B12: 实施计划与里程碑设置 | C12: 7 | D12: 阶段划分、里程碑、关键交付节点清晰可执行，得 7 分；较清晰，得 4-6 分；安排粗略，得 0-3 分。 | E12: WBS、里程碑计划、甘特图。
B13: 风险控制与质量保证 | C13: 5 | D13: 具备完整的风险识别、预警、应对和质量控制机制，得 5 分；机制基本可行，得 3-4 分；机制缺失，得 0-2 分。 | E13: 风险台账、测试策略、质量控制流程。
B14: 交付物定义与验收安排 | C14: 5 | D14: 交付物清单、输出形式、验收方式明确，得 5 分；基本明确，得 3-4 分；不明确，得 0-2 分。 | E14: 交付物清单、验收计划、文档目录。
A15: 团队配置与履约能力 | B15: 项目经理与核心骨干匹配度 | C15: 7 | D15: 项目经理及核心成员经验丰富、履历与项目高度匹配，得 7 分；基本匹配，得 4-6 分；匹配度较低，得 0-3 分。 | E15: 人员简历、项目经历、证书、社保证明。
B16: 岗位配置完整性 | C16: 5 | D16: 产品、设计、开发、测试、实施等关键岗位配置齐全且职责清晰，得 5 分；基本齐备，得 3-4 分；明显缺失，得 0-2 分。 | E16: 组织架构图、岗位分工、人员清单。
B17: 驻场/协同与资源保障能力 | C17: 5 | D17: 驻场计划、协同机制、替补资源保障合理，得 5 分；一般，得 3-4 分；保障不足，得 0-2 分。 | E17: 驻场计划、协同机制、替补安排。
A18: 同类业绩与资质能力 | B18: 同类案例数量与相关性 | C18: 8 | D18: 同类案例数量充足、与本项目行业和复杂度高度相关，得 8 分；相关性一般，得 4-7 分；较弱，得 0-3 分。 | E18: 合同关键页、验收证明、发票或回款证明。
B19: 业绩证明完整性 | C19: 3 | D19: 案例证明材料齐全、可核验，得 3 分；部分缺失，得 2 分；证明不足，得 0-1 分。 | E19: 合同、验收、佐证清单。
B20: 专业资质与质量体系 | C20: 5 | D20: 具备与项目匹配的体系认证或专业资质，且有效性明确，得 5 分；资质较少或匹配度一般，得 3-4 分；无有效资质，得 0-2 分。 | E20: ISO、CMMI、软件企业能力或行业资质证明。
A21: 服务承诺与文件质量 | B21: 售后服务、响应与质保承诺 | C21: 5 | D21: 售后机制、响应时效、质保范围和服务边界明确，得 5 分；一般，得 3-4 分；承诺不明确，得 0-2 分。 | E21: 售后服务方案、承诺函、SLA。
B22: 响应文件完整性与规范性 | C22: 3 | D22: 文件结构清楚、内容完整、查阅方便、格式规范，得 3 分；一般，得 2 分；较差，得 0-1 分。 | E22: 响应文件目录、排版、盖章签字情况。
A23: 技术商务小计 | C23: 100 | D23: 本行自动汇总本页技术商务得分，不含统一报价得分。 | F23: =ROUND(SUM(F5:F22),2) -> 0 | G23: =ROUND(SUM(G5:G22),2) -> 0 | H23: =ROUND(SUM(H5:H22),2) -> 0

Sheet 驻场运维评分
A1: 驻场运维评分
A2: 适用于以驻场研发、运维支持、持续服务和响应保障为主的项目。本页技术商务细项采用整数分值分配，页内满分 100 分。
A3: 填写规则：仅录入蓝色单元格；专家原始分不得超过 C 列分值；本页仅统计技术商务分，不含统一报价得分。
A4: 评审大项 | B4: 评审子项 | C4: 分值 | D4: 评分标准 | E4: 评分依据/证明材料 | F4: 诚迈科技原始分 | G4: 晶石科技原始分 | H4: 亿顺弘原始分 | I4: 备注
A5: 服务理解与方案设计 | B5: 服务范围与边界理解 | C5: 7 | D5: 对服务范围、职责边界、支持边界理解准确，得 7 分；基本准确，得 4-6 分；理解偏差明显，得 0-3 分。 | E5: 服务方案、范围说明、职责分工。
B6: 服务流程与报告机制 | C6: 5 | D6: 服务流程、工单流转、例会与报告机制完整，得 5 分；基本具备，得 3-4 分；机制不足，得 0-2 分。 | E6: 服务流程图、报告模板、例会机制。
B7: 服务方案可执行性 | C7: 5 | D7: 方案执行路径清晰、适配采购场景，得 5 分；一般，得 3-4 分；可执行性弱，得 0-2 分。 | E7: 实施路径、现场协同方案。
A8: 驻场与响应保障 | B8: 驻场人员数量与岗位结构 | C8: 10 | D8: 驻场人员数量充分、岗位结构合理、关键岗位齐备，得 10 分；基本满足，得 5-9 分；明显不足，得 0-4 分。 | E8: 驻场清单、岗位说明、资源投入计划。
B9: 人员稳定性与替补机制 | C9: 7 | D9: 稳定性保障和替补机制明确，得 7 分；较为明确，得 4-6 分；安排不足，得 0-3 分。 | E9: 替补名单、稳定性承诺、人员管理机制。
B10: 响应时效与故障升级机制 | C10: 10 | D10: 响应时效、升级路径、闭环机制明确且优于基本要求，得 10 分；基本满足，得 5-9 分；较弱，得 0-4 分。 | E10: SLA、升级流程、值守安排。
B11: 应急保障与重大问题处置能力 | C11: 7 | D11: 应急预案、重大故障处置、专项支撑能力强，得 7 分；一般，得 4-6 分；较弱，得 0-3 分。 | E11: 应急预案、值班机制、历史案例说明。
A12: 持续服务与知识交接 | B12: 知识库、文档与培训交接安排 | C12: 8 | D12: 知识沉淀、文档维护、培训交接安排完整，得 8 分；较完整，得 4-7 分；较弱，得 0-3 分。 | E12: 知识库目录、交接计划、培训方案。
B13: 持续优化与例会复盘机制 | C13: 8 | D13: 具备持续优化、例会复盘、改进闭环机制，得 8 分；一般，得 4-7 分；机制不足，得 0-3 分。 | E13: 复盘模板、改进机制、周/月报样例。
A14: 同类经验与资质能力 | B14: 同类服务案例数量与相关性 | C14: 10 | D14: 同类服务案例丰富且相关性高，得 10 分；一般，得 5-9 分；较弱，得 0-4 分。 | E14: 服务合同、验收证明、用户评价或成果材料。
B15: 资质与服务管理体系 | C15: 7 | D15: 具备与服务管理相关的体系认证或有效资质，得 7 分；一般，得 4-6 分；无有效资质，得 0-3 分。 | E15: ISO20000、ISO27001、质量体系等。
A16: 商务响应与文件质量 | B16: 商务承诺与违约响应机制 | C16: 7 | D16: 商务承诺明确、违约处理和资源补偿机制清晰，得 7 分；一般，得 4-6 分；较弱，得 0-3 分。 | E16: 商务承诺函、违约处理条款响应。
B17: 文件完整性与规范性 | C17: 9 | D17: 文件完整、结构清晰、排版规范、检索方便，得 9 分；一般，得 5-8 分；较弱，得 0-4 分。 | E17: 响应文件目录、盖章签字、版本控制。
A18: 技术商务小计 | C18: 100 | D18: 本行自动汇总本页技术商务得分，不含统一报价得分。 | F18: =ROUND(SUM(F5:F17),2) -> 0 | G18: =ROUND(SUM(G5:G17),2) -> 0 | H18: =ROUND(SUM(H5:H17),2) -> 0

Sheet 统一报价评分
A1: 统一报价评分
A2: 适用于本项目整包统一报价评分。供应商仅填写一份针对本次项目完整范围的有效报价；本页默认满分 100 分。 | J2: 诚迈科技有效报价 | K2: 晶石科技有效报价 | L2: 亿顺弘有效报价
A3: 填写规则：仅录入蓝色单元格；报价应为本项目整包统一有效报价，不再区分定制开发和驻场运维分别报价。
A4: 评审大项 | B4: 评审子项 | C4: 分值 | D4: 评分标准 | E4: 评分依据/证明材料 | F4: 诚迈科技得分 | G4: 晶石科技得分 | H4: 亿顺弘得分 | I4: 备注
A5: 价格评分 | B5: 统一报价得分 | C5: 100 | D5: 价格部分采用最低有效报价比例法，最低有效报价得满分 100 分，其他供应商按“最低有效报价/本供应商有效报价×100”折算。 | E5: 有效报价表、澄清函、报价一览表等。 | F5: =IF(OR($J$3="",COUNT($J$3:$L$3)=0),0,ROUND(MIN($J$3:$L$3)/$J$3*100,2)) -> 0 | G5: =IF(OR($K$3="",COUNT($J$3:$L$3)=0),0,ROUND(MIN($J$3:$L$3)/$K$3*100,2)) -> 0 | H5: =IF(OR($L$3="",COUNT($J$3:$L$3)=0),0,ROUND(MIN($J$3:$L$3)/$L$3*100,2)) -> 0
A6: 合计 | C6: 100 | D6: 本页满分 100 分。 | F6: =ROUND(F5,2) -> 0 | G6: =ROUND(G5,2) -> 0 | H6: =ROUND(H5,2) -> 0

Sheet 汇总排名
A1: 综合评审汇总及排名
A3: 项目统一权重设置 | B3: 数值 | C3: 说明
A4: 定制开发权重（%） | B4: 40
A5: 驻场运维权重（%） | B5: 20
A6: 统一报价权重（%） | B6: 40
A7: 权重合计（%） | B7: =SUM(B4:B6) -> 100
A8: 权重使用规则
A10: 指标 | B10: 供应商A | C10: 供应商B | D10: 供应商C | E10: 说明
A11: 资格审查结论 | B11: =资格审查!D15 -> 待确认 | C11: =资格审查!E15 -> 待确认 | D11: =资格审查!F15 -> 待确认 | E11: 仅资格审查“通过”的供应商参与排序。
A12: 定制开发总分 | B12: =IF(B11="通过",定制开发评分!F23,"") | C12: =IF(C11="通过",定制开发评分!G23,"") | D12: =IF(D11="通过",定制开发评分!H23,"") | E12: 引用“定制开发评分”页技术商务小计，满分 100 分。
A13: 驻场运维总分 | B13: =IF(B11="通过",驻场运维评分!F18,"") | C13: =IF(C11="通过",驻场运维评分!G18,"") | D13: =IF(D11="通过",驻场运维评分!H18,"") | E13: 引用“驻场运维评分”页技术商务小计，满分 100 分。
A14: 统一报价总分 | B14: =IF(B11="通过",统一报价评分!F6,"") | C14: =IF(C11="通过",统一报价评分!G6,"") | D14: =IF(D11="通过",统一报价评分!H6,"") | E14: 引用“统一报价评分”页合计分，满分 100 分。
A15: 综合评审得分 | B15: =IF(B11="通过",ROUND(B12*$B$4/100+B13*$B$5/100+B14*$B$6/100,2),"") | C15: =IF(C11="通过",ROUND(C12*$B$4/100+C13*$B$5/100+C14*$B$6/100,2),"") | D15: =IF(D11="通过",ROUND(D12*$B$4/100+D13*$B$5/100+D14*$B$6/100,2),"") | E15: 综合得分=定制开发总分×定制开发权重+驻场运维总分×驻场运维权重+统一报价总分×统一报价权重。
A16: 综合排名 | B16: =IF(B11="通过",RANK(B15,$B$15:$D$15,0),"") | C16: =IF(C11="通过",RANK(C15,$B$15:$D$15,0),"") | D16: =IF(D11="通过",RANK(D15,$B$15:$D$15,0),"") | E16: 按综合得分由高到低排名，分值相同则并列。
A19: 补充说明
A20: 1. 如项目只适用一种评分页，可将其他评分页权重设置为 0。
A21: 2. 请确保 B4:B6 三项权重合计为 100；B7 为自动校验值。
A22: 3. 如采购文件采用基准价法或其他价格评审办法，应在“统一报价评分”页统一替换价格公式。
A23: 4. 本模板为通用正式版，项目特有的资质门槛、涉密要求、原厂授权要求应根据采购文件另行补充。
